README.md
setup.py
whichip.py
whichip.egg-info/PKG-INFO
whichip.egg-info/SOURCES.txt
whichip.egg-info/dependency_links.txt
whichip.egg-info/entry_points.txt
whichip.egg-info/top_level.txt